[
  {
    "dataToDelete": "                                "
  },
  {
    "dataToDelete": "% & ( ) / - ."
  },
  {
    "dataToDelete": "Jollibee Filipino Sweet Style"
  },
  {
    "dataToDelete": "This is a very long string that exceeds the maximum allowed length."
  },
  {
    "dataToDelete": "© ™ ® à á â ñ ä ¢ £ ¥ € ! @ #"
  },
  {
    "dataToDelete": "© ™ ® à á â ñ ä ¢ £ ¥ € ! @ # $ ^ * _ + = < > ? `"
  },
  {
    "dataToDelete": "Jollibee Filipino Sweet Style Spaghetti Langhap Sa"
  },
  {
    "dataToDelete": "© ™ ® à á â ñ ä ¢ £ ¥ € ! @ # $ ^ * _ + = < > ? ` \\ ~ \\\" | \\ ] [ ] ; :"
  },
  {
    "dataToDelete": "WINTERHOLIDAY50PERCENTDISCOUNT"
  },
  {
    "dataToDelete": "© ™ ® à á â ñ ä ¢ £ ¥ € ! @ #"
  },
  {
    "dataToDelete": "Delicious and crispy Chickenjoy with a side of Jolly Spaghetti and garlic rice, perfect for a fulfil"
  },
  {
    "dataToDelete": "Jollibee Filipino Sweet Style Spaghetti Langhap Sarap"
  },
  {
    "dataToDelete": "© ™ ® à á â ñ ä ¢ £ ¥ € ! @ # $ ^ * _ + = < > ? ` ~ \" | \\ [ ] ; :"
  },
  {
    "dataToDelete": "©™®àáâñä¢£¥€!@#$^*_+=<>?`\\~\\\"|\\][];:"
  },
  {
    "dataToDelete": "% & ( ) / - "
  },
  {
    "dataToDelete": "This is a very long string that exceeds the maximu"
  },
  {
    "dataToDelete": "% & ( ) / -"
  },
  {
    "dataToDelete": "WINTERHOLIDAY50PERCENTDISCOUNTFORALLITEMSOVER1000P"
  }
]