[
  {
    "itemSubclass": "© ™ ® à á â ñ ä ¢ £ ¥ € ! @ # $ ^ * _ + = < > ? ` ~ \" | \\ [ ] ; :",
    "itemClass": "Food"
  },
  {
    "itemSubclass": "Mashed Potatoes",
    "itemClass": "Food",
    "editItemSubclass": "Snacks",
    "editItemClass": "Food"
  },
  {
    "itemSubclass": "Breakfast Meal",
    "itemClass": "Food"
  },
  {
    "itemSubclass": "Milkshakes",
    "itemClass": "Beverages"
  },
  {
    "itemSubclass": "Chicken",
    "itemClass": "Food"
  },
  {
    "itemSubclass": "Burger",
    "itemClass": "Food"
  },
  {
    "itemSubclass": "Spaghetti",
    "itemClass": "Food"
  },
  {
    "itemSubclass": "Rice Meals",
    "itemClass": "Food"
  },
  {
    "itemSubclass": "Pies",
    "itemClass": "Dessert"
  },
  {
    "itemSubclass": "Ice Cream",
    "itemClass": "Dessert"
  },
  {
    "itemSubclass": "Soft Drinks",
    "itemClass": "Beverages"
  },
  {
    "itemSubclass": "Coffee",
    "itemClass": "Beverages"
  },
  {
    "itemSubclass": "Juices",
    "itemClass": "Beverages"
  },
  {
    "itemSubclass": "Sides",
    "itemClass": "Food"
  },
  {
    "itemSubclass": "Family Super Meals",
    "itemClass": "Food"
  },
  {
    "itemSubclass": "% & ( ) / - .",
    "itemClass": "Beverages"
  },
  {
    "itemSubclass": "null",
    "itemClass": "Food"
  },
  {
    "itemSubclass": "Jollibee Filipino Sweet Style Spaghetti Langhap Sarap",
    "itemClass": "Food"
  }
]