[
  {
    "subtotal": 76,
    "discount": 0,
    "lessVatAdj": 0,
    "serviceCharge": 6.78571428571428,
    "serviceChargeDiscount": 0,
    "total": 82.7857142857143
  },
  {
    "subtotal": 204,
    "discount": 20.4,
    "lessVatAdj": 0,
    "serviceCharge": 18.2142857142857,
    "serviceChargeDiscount": 0,
    "total": 201.814285714286
  },
  {
    "subtotal": 210,
    "discount": 42,
    "lessVatAdj": 0,
    "serviceCharge": 18.76,
    "serviceChargeDiscount": 0,
    "total": 186.76
  },
  {
    "subtotal": 87,
    "discount": 15.5357142857143,
    "lessVatAdj": 9.32142857142857,
    "serviceCharge": 7.76,
    "serviceChargeDiscount": 1.55357142857143,
    "total": 68.35
  },
  {
    "subtotal": 222,
    "discount": 39.65,
    "lessVatAdj": 23.78,
    "serviceCharge": 19.8214285714286,
    "serviceChargeDiscount": 3.96428571428571,
    "total": 174.428571428571
  },
  {
    "subtotal": 96,
    "discount": 17.1428571428571,
    "lessVatAdj": 0,
    "serviceCharge": 8.57142857142857,
    "serviceChargeDiscount": 1.71428571428571,
    "total": 85.72
  },
  {
    "subtotal": 109,
    "discount": 21.8,
    "lessVatAdj": 0,
    "serviceCharge": 9.73214285714286,
    "serviceChargeDiscount": 0,
    "total": 96.9321428571429
  },
  {
    "subtotal": 150,
    "discount": 0,
    "lessVatAdj": 16.0714285714286,
    "serviceCharge": 13.3928571428571,
    "serviceChargeDiscount": 0,
    "total": 147.321428571429
  },
  {
    "subtotal": 599,
    "discount": 17.8571428571429,
    "lessVatAdj": 10.7142857142857,
    "serviceCharge": 53.4821428571429,
    "serviceChargeDiscount": 1.78571428571429,
    "total": 622.125
  },
  {
    "subtotal": 799,
    "discount": 35.7142857142857,
    "lessVatAdj": 21.4285714285714,
    "serviceCharge": 71.3392857142857,
    "serviceChargeDiscount": 3.5714285714285716,
    "total": 809.625
  },
  {
    "subtotal": 399,
    "discount": 71.25,
    "lessVatAdj": 42.75,
    "serviceCharge": 35.62499999999999,
    "serviceChargeDiscount": 7.124999999999999,
    "total": 313.5
  },
  {
    "subtotal": 499,
    "discount": 89.1071428571428,
    "lessVatAdj": 53.4642857142857,
    "serviceCharge": 44.5535714285714,
    "serviceChargeDiscount": 8.910714285714281,
    "total": 392.0714285714286
  },
  {
    "subtotal": 300,
    "discount": 0,
    "lessVatAdj": 0,
    "serviceCharge": 26.78,
    "serviceChargeDiscount": 0,
    "total": 326.78
  },
  {
    "subtotal": 170,
    "discount": 17,
    "lessVatAdj": 0,
    "serviceCharge": 15.17,
    "serviceChargeDiscount": 0,
    "total": 168.17
  },
  {
    "subtotal": 42,
    "discount": 8.4,
    "lessVatAdj": 0,
    "serviceCharge": 3.75,
    "serviceChargeDiscount": 0,
    "total": 37.35
  },
  {
    "subtotal": 320,
    "discount": 57.1428571428571,
    "lessVatAdj": 34.2857142857143,
    "serviceCharge": 28.5714285714286,
    "serviceChargeDiscount": 5.714285714285721,
    "total": 251.42857142857144
  },
  {
    "subtotal": 30,
    "discount": 5.35714285714286,
    "lessVatAdj": 3.21428571428571,
    "serviceCharge": 2.67857142857143,
    "serviceChargeDiscount": 0.535714285714286,
    "total": 23.571428571428577
  },
  {
    "subtotal": 60,
    "discount": 10.7142857142857,
    "lessVatAdj": 0,
    "serviceCharge": 5.35714285714286,
    "serviceChargeDiscount": 1.071428571428572,
    "total": 53.58
  },
  {
    "subtotal": 49,
    "discount": 9.8,
    "lessVatAdj": 0,
    "serviceCharge": 4.37,
    "serviceChargeDiscount": 0,
    "total": 43.57
  },
  {
    "subtotal": 50,
    "discount": 0,
    "lessVatAdj": 5.35714285714286,
    "serviceCharge": 4.46428571428571,
    "serviceChargeDiscount": 0,
    "total": 49.1071428571429
  },
  {
    "subtotal": 599,
    "discount": 17.8571428571429,
    "lessVatAdj": 10.7142857142857,
    "serviceCharge": 53.4821428571429,
    "serviceChargeDiscount": 1.7857142857142858,
    "total": 622.125
  },
  {
    "subtotal": 799,
    "discount": 35.7142857142857,
    "lessVatAdj": 21.4285714285714,
    "serviceCharge": 71.3392857142857,
    "serviceChargeDiscount": 3.5714285714285716,
    "total": 809.625
  },
  {
    "subtotal": 105,
    "discount": 0,
    "lessVatAdj": 0,
    "serviceCharge": 9.38,
    "serviceChargeDiscount": 0,
    "total": 114.38
  },
  {
    "subtotal": 99,
    "discount": 9.9,
    "lessVatAdj": 0,
    "serviceCharge": 8.839285714285714,
    "serviceChargeDiscount": 0,
    "total": 97.9392857142857
  },
  {
    "subtotal": 99,
    "discount": 19.8,
    "lessVatAdj": 0,
    "serviceCharge": 8.83928571428571,
    "serviceChargeDiscount": 0,
    "total": 88.0392857142857
  },
  {
    "subtotal": 125,
    "discount": 22.3214285714286,
    "lessVatAdj": 13.3928571428571,
    "serviceCharge": 11.1607142857143,
    "serviceChargeDiscount": 2.23214285714286,
    "total": 98.2142857142857
  },
  {
    "subtotal": 152,
    "discount": 27.1428571428571,
    "lessVatAdj": 16.2857142857143,
    "serviceCharge": 13.5714285714286,
    "serviceChargeDiscount": 2.71428571428571,
    "total": 119.428571428571
  },
  {
    "subtotal": 105,
    "discount": 18.75,
    "lessVatAdj": 0,
    "serviceCharge": 9.375,
    "serviceChargeDiscount": 1.875,
    "total": 93.75
  },
  {
    "subtotal": 125,
    "discount": 25,
    "lessVatAdj": 0,
    "serviceCharge": 11.1607142857143,
    "serviceChargeDiscount": 0,
    "total": 111.160714285714
  },
  {
    "subtotal": 95,
    "discount": 0,
    "lessVatAdj": 10.1785714285714,
    "serviceCharge": 8.48214285714286,
    "serviceChargeDiscount": 0,
    "total": 93.3035714285714
  },
  {
    "subtotal": 599,
    "discount": 17.8571428571429,
    "lessVatAdj": 10.7142857142857,
    "serviceCharge": 53.4821428571429,
    "serviceChargeDiscount": 1.78571428571429,
    "total": 622.125
  },
  {
    "subtotal": 799,
    "discount": 35.7142857142857,
    "lessVatAdj": 21.4285714285714,
    "serviceCharge": 71.3392857142857,
    "serviceChargeDiscount": 3.57142857142857,
    "total": 809.625
  },
  {
    "subtotal": 32,
    "discount": 0,
    "lessVatAdj": 0,
    "serviceCharge": 2.85714285714286,
    "serviceChargeDiscount": 0,
    "total": 34.8571428571429
  }
]