[
  {
    "selectorName": "Time Textbox",
    "sel": "#timestart",
    "assertion": "not.be.disabled"
  },
  {
    "sel": "button.px-4.py-2.rounded.border.border-solid.border-gray-500.hover\\\\:bg-red-500.hover\\\\:text-white.my-5.mxl-3",
    "assertion": "not.be.disabled"
  },
  {
    "sel": "button.px-4.py-2.rounded.border.border-solid#button-form-2.hover\\\\:bg-blue-500.hover\\\\:text-white.my-5.mx-3",
    "assertion": "not.be.disabled"
  },
  {
    "assertion": "not.be.disabled"
  },
  {
    "assertion": "not.be.disabled"
  },
  {
    "assertion": "not.be.disabled"
  },
  {
    "assertion": "not.be.disabled"
  },
  {
    "assertion": "not.be.enabled"
  },
  {
    "assertion": "not.be.enabled"
  },
  {
    "assertion": "not.be.disabled"
  }
]